{"title": "Recurso de inconstitucionalidad n.\u00ba 2007-2012, contra el art\u00edculo 23 del Real Decreto-ley 8/2011, de 1 de julio, de medidas de apoyo a los deudores hipotecarios, de control del gasto p\u00fablico y cancelaci\u00f3n de deudas con empresas y aut\u00f3nomos contra\u00eddas por las entidades locales, de fomento de la actividad empresarial e impulso de la rehabilitaci\u00f3n y de simplificaci\u00f3n administrativa.", "url": "http://www.boe.es/diario_boe/txt.php?id=BOE-A-2012-6687", "analisys": ["Rango: Providencia (Recurso de Inconstitucionalidad)", "Fecha de disposici\u00f3n: 08/05/2012", "Fecha de publicaci\u00f3n: 21/05/2012"], "content": "\nTEXTO\n\nEl Pleno del Tribunal Constitucional, por providencia de 8 de mayo actual, ha acordado admitir a tr\u00e1mite el recurso de inconstitucionalidad n\u00famero 2007-2012, promovido por el Gobierno de Canarias, contra el art\u00edculo 23 del Real Decreto-ley 8/2011, de 1 de julio, de medidas de apoyo a los deudores hipotecarios, de control del gasto p\u00fablico y cancelaci\u00f3n de deudas con empresas y aut\u00f3nomos contra\u00eddas por las entidades locales, de fomento de la actividad empresarial e impulso de la rehabilitaci\u00f3n y de simplificaci\u00f3n administrativa.\nMadrid, 8 de mayo de 2012.\u2013La Secretaria de Justicia del Pleno del Tribunal Constitucional, Herminia Palencia Guerra.\n\n #textoxslt \n", "pdf": "http://www.boe.es/boe/dias/2012/05/21/pdfs/BOE-A-2012-6687.pdf", "more": {"Materias": ["Autorizaciones", "Obras", "Procedimiento administrativo", "Suelo"], "Referencias anteriores": ["RECURSO promovido contra el art. 23 del REAL DECRETO-LEY 8/2011, de 1 de julio (Ref. BOE-A-2011-11641)."]}}