{"title": "Recurso de inconstitucionalidad n.\u00ba 6084-2012, contra el Real Decreto-ley 1/2012, de 27 de enero, por el que se procede a la suspensi\u00f3n de los procedimientos de preasignaci\u00f3n de retribuci\u00f3n y a la supresi\u00f3n de los incentivos econ\u00f3micos para nuevas instalaciones de producci\u00f3n de energ\u00eda el\u00e9ctrica a partir de cogeneraci\u00f3n, fuentes de energ\u00eda renovables y residuos.", "url": "http://www.boe.es/diario_boe/txt.php?id=BOE-A-2012-14403", "analisys": ["Rango: Providencia (Recurso de Inconstitucionalidad)", "Fecha de disposici\u00f3n: 13/11/2012", "Fecha de publicaci\u00f3n: 23/11/2012"], "content": "\nTEXTO\n\nEl Pleno del Tribunal Constitucional, por providencia de 13 de noviembre actual, ha acordado admitir a tr\u00e1mite el recurso de inconstitucionalidad n\u00famero 6084-2012, promovido por el Gobierno de Canarias contra el Real Decreto-ley 1/2012, de 27 de enero, por el que se procede a la suspensi\u00f3n de los procedimientos de preasignaci\u00f3n de retribuci\u00f3n y a la supresi\u00f3n de los incentivos econ\u00f3micos para nuevas instalaciones de producci\u00f3n de energ\u00eda el\u00e9ctrica a partir de cogeneraci\u00f3n, fuentes de energ\u00eda renovables y residuos.\nMadrid, 13 de noviembre de 2012.\u2013La Secretaria de Justicia del Pleno del Tribunal Constitucional, Herminia Palencia Guerra.\n\n #textoxslt \n", "pdf": "http://www.boe.es/boe/dias/2012/11/23/pdfs/BOE-A-2012-14403.pdf", "more": {"Materias": ["Ayudas", "Energ\u00eda el\u00e9ctrica", "Pol\u00edtica energ\u00e9tica", "Producci\u00f3n de energ\u00eda", "Recursos de inconstitucionalidad"], "Referencias anteriores": ["RECURSO promovido contra el REAL DECRETO-LEY 1/2012, de 27 de enero (Ref. BOE-A-2012-1310)."]}}